.travis.yml
AUTHORS
ChangeLog
LICENSE
MANIFEST.in
README.md
requirements.txt
setup.cfg
setup.py
doc/.gitignore
doc/conf.py
doc/index.rst
doc/requirements.txt
etc/config.yml
fabnodes/__init__.py
fabnodes/__main__.py
fabnodes/__version__.py
fabnodes/cli.py
fabnodes.egg-info/PKG-INFO
fabnodes.egg-info/SOURCES.txt
fabnodes.egg-info/dependency_links.txt
fabnodes.egg-info/entry_points.txt
fabnodes.egg-info/not-zip-safe
fabnodes.egg-info/pbr.json
fabnodes.egg-info/requires.txt
fabnodes.egg-info/top_level.txt
fabnodes/core/__init__.py
fabnodes/core/config.py
fabnodes/core/logger.py
fabnodes/lib/__init__.py
fabnodes/lib/actions.py
fabnodes/lib/common.py
fabnodes/lib/decorators.py
fabnodes/lib/filesystem.py
fabnodes/lib/stack.py
fabnodes/lib/util.py
fabnodes/templates/cfndsl.rb.j2
fabnodes/templates/code_bucket.rb.j2
fabnodes/tests/__init__.py
samples/basic_node/node.py
samples/basic_node/node.yaml
samples/basic_node/requirements.txt
test/.gitignore
test/pytest.ini
test/requirements.txt
test/fabnodes/test_cli.py
test/fabnodes/core/test_config.py
test/fabnodes/core/test_logger.py