Metadata-Version: 2.1
Name: fabnodes
Version: 0.0.7
Summary: UNKNOWN
Home-page: https://github.com/roaet/fabnodes
Author: Justin Hammond
Author-email: runningempty@gmail.com
License: MIT
Platform: UNKNOWN
Classifier: Development Status :: 2 - Pre-Alpha
Classifier: Environment :: Console
Classifier: Intended Audience :: Developers
Classifier: Intended Audience :: Information Technology
Classifier: License :: OSI Approved :: Apache Software License
Classifier: Operating System :: OS Independent
Classifier: Programming Language :: Python
